{
    "colors": [
        {
            "color": "red",
            "range": [
                [
                    [0, 230, 30],
                    [1, 255, 135]
                ],
                [
                    [178, 230, 30],
                    [180, 255, 135]
                ]
            ]
        },
        {
            "color": "yellow",
            "range": [
                [
                    [18, 160, 120],
                    [24, 245, 220]
                ]
            ]
        },
        {
            "color": "green",
            "range": [
                [
                    [72, 150, 40],
                    [84, 225, 112]
                ]
            ]
        },
        {
            "color": "blue",
            "range": [
                [
                    [100, 145, 60],
                    [115, 196, 135]
                ]
            ]
        },
        {
            "color": "orange",
            "range": [
                [
                    [3, 230, 90],
                    [12, 255, 200]
                ]
            ]
        }
    ]
}
